<?xml version="1.0"?>
<api>
	<description>
		<![CDATA[This is an API to interact with MentorWeb database]]>
	</description>

	<command id='user' security='protected'>
		<description><![CDATA[This API lets you interact with the MentorWeb database]]></description>
		
		<index>
			<description><![CDATA[This is how you can get a listing of all users]]></description>
			
			<action file='mentorweb.php'><![CDATA[listUsers();]]></action>
		</index>
		<command id='match' security='protected'>
			<index><!-- index specicifies what happens when get is called with no parameters -->
				<action file='mentorweb.php'><![CDATA[listUserMatches($_REST['user']);]]></action>
			</index>
			<get>
				<action file='mentorweb.php'><![CDATA[getUserMatch($_REST['user'], $_REST['user/match']);]]></action>
			</get>
		</command>
	</command>

	<command id='match' security='protected'>
		<description><![CDATA[This simple API lets interact with the Mentor Web database by creating/editing matches]]></description>
		
		<index>
			<description><![CDATA[This is how you can get a listing of all matches]]></description>
			
			<action file='mentorweb.php'><![CDATA[listMatches();]]></action>
		</index>
		
		<get>
			<description><![CDATA[This is how you can get a specific match]]></description>
			
			<action file='mentorweb.php'><![CDATA[getMatch($_REST['match']);]]></action>
		</get>
		
		<post>
			<description><![CDATA[This is how you can create a match]]></description>
			
			<action file='mentorweb.php'><![CDATA[addMatch($_POST['makeMatch']);]]></action>
		</post>
		
		<put>
			<description><![CDATA[This is how you can update a match]]></description>
			
			<action file='mentorweb.php'><![CDATA[updateComment($_REST['match'],$_POST['makeMatch']);]]></action><!-- comment  and commentText-->
		</put>
		
		<delete>
			<description><![CDATA[This is how you can delete a match]]></description>
			
			<action file='mentorweb.php'><![CDATA[deleteMatch($_REST['match']);]]></action><!-- match -->
		</delete>
	</command>
</api>
